Metadata-Version: 2.1
Name: django-segno-qr
Version: 1.0.1
Summary: Django template tag for generating QR codes using segno
Home-page: https://github.com/ideler/django-segno-qr
Author: Ideler IT-Service GmbH
Author-email: hosting@ideler.de
License: UNKNOWN
Platform: UNKNOWN
Classifier: Programming Language :: Python :: 3
Classifier: License :: OSI Approved :: MIT License
Classifier: Operating System :: OS Independent
Classifier: Framework :: Django :: 3.0
Requires-Python: >=3
